bin/enforcer
build/lib/tests/__init__.py
build/lib/tests/test_import.py
build/lib/tests/test_secret.py
build/lib/tests/chunks/__init__.py
build/lib/tests/chunks/test_chunks.py
build/lib/tests/upload/__init__.py
build/lib/tests/upload/test_secret_key_pattern.py
build/lib/upside/__init__.py
build/lib/upside/enforcer/__init__.py
build/lib/upside/enforcer/app.py
build/lib/upside/enforcer/config.py
build/lib/upside/enforcer/upload/__init__.py
build/lib/upside/enforcer/upload/chunks.py
build/lib/upside/enforcer/upload/cli.py
build/lib/upside/enforcer/upload/util.py
build/lib/upside/enforcer/util/__init__.py
build/lib/upside/enforcer/util/auth.py
build/lib/upside/enforcer/util/secret.py
build/lib/upside/enforcer/util/tags.py
enforcer-1.0.1.data/scripts/enforcer
tests/__init__.py
tests/test_import.py
tests/test_secret.py
tests/chunks/__init__.py
tests/chunks/test_chunks.py
tests/upload/__init__.py
tests/upload/test_secret_key_pattern.py
upside/__init__.py
upside/enforcer/__init__.py
upside/enforcer/app.py
upside/enforcer/config.py
upside/enforcer/upload/__init__.py
upside/enforcer/upload/chunks.py
upside/enforcer/upload/cli.py
upside/enforcer/upload/util.py
upside/enforcer/util/__init__.py
upside/enforcer/util/auth.py
upside/enforcer/util/secret.py
upside/enforcer/util/tags.py
enforcer-1.0.1.dist-info/AUTHORS.md
enforcer-1.0.1.dist-info/LICENSE
enforcer-1.0.1.dist-info/METADATA
enforcer-1.0.1.dist-info/WHEEL
enforcer-1.0.1.dist-info/top_level.txt
enforcer-1.0.1.dist-info/RECORD
