Metadata-Version: 2.1
Name: enforcer
Version: 1.0.1
Summary: AWS SSM Parameter Store Management CLI
Home-page: https://github.com/PotomacInnovation/enforcer
Author: @PotomacInnovation/owners-sre
License: Upside
Platform: any
Requires-Dist: python-dotenv (~=0.7.1)
Requires-Dist: boto3 (==1.9.66)
Requires-Dist: pyperclip (==1.7.0)
Requires-Dist: click (==7.0)
Requires-Dist: colorama (==0.4.1)
Provides-Extra: dev
Requires-Dist: flake8 (~=3.5.0) ; extra == 'dev'
Requires-Dist: mock (~=2.0.0) ; extra == 'dev'
Requires-Dist: moto (==1.3.1) ; extra == 'dev'
Requires-Dist: pytest (~=3.4.0) ; extra == 'dev'
Requires-Dist: pytest-cov (~=2.5.1) ; extra == 'dev'
Requires-Dist: tox (~=2.9.1) ; extra == 'dev'
Requires-Dist: yapf (~=0.21.0) ; extra == 'dev'
Requires-Dist: bandit (==1.5.1) ; extra == 'dev'
